pddlutils/__init__.py
pddlutils/grounding.py
pddlutils/progression.py
pddlutils/utils.py
pddl_utils-0.0.1.dist-info/LICENSE
pddl_utils-0.0.1.dist-info/METADATA
pddl_utils-0.0.1.dist-info/WHEEL
pddl_utils-0.0.1.dist-info/top_level.txt
pddl_utils-0.0.1.dist-info/RECORD
