Metadata-Version: 2.1
Name: pddl-utils
Version: 0.0.1
Summary: Library of miscellaneous utilies to work with PDDL (both in Python and on the command line).
Home-page: https://github.com/AI-Planning/pddl-utils
Author: Christian Muise
Author-email: christian.muise@gmail.com
License: MIT
Classifier: Programming Language :: Python :: 3
Classifier: License :: OSI Approved :: MIT License
Classifier: Operating System :: OS Independent
Requires-Python: >=3.10
License-File: LICENSE
Requires-Dist: pddl
